machc/base/__init__.py
machc/base/contact/__init__.py
machc/base/contact/address.py
machc/base/identifier/__init__.py
machc/base/identifier/entity.py
machc_base-0.0.2.dist-info/METADATA
machc_base-0.0.2.dist-info/WHEEL
machc_base-0.0.2.dist-info/top_level.txt
machc_base-0.0.2.dist-info/RECORD
