Metadata-Version: 2.4
Name: machc.base
Version: 0.0.2
Summary: Provides base entities.
Author-email: Viktor Tovstyi <viktor.tovstyi@gmail.com>
Requires-Python: ==3.12.3
